pyflop/__init__.py
pyflop/pyflop.py
tests/__init__.py
tests/test_pyflop.py
pyflop-1.1.1.dist-info/LICENSE
pyflop-1.1.1.dist-info/METADATA
pyflop-1.1.1.dist-info/WHEEL
pyflop-1.1.1.dist-info/entry_points.txt
pyflop-1.1.1.dist-info/top_level.txt
pyflop-1.1.1.dist-info/RECORD
