Metadata-Version: 2.1
Name: pyflop
Version: 1.1.1
Requires-Python: >=3.9
License-File: LICENSE
Requires-Dist: hostsed
